notion2obsidian/__init__.py
notion2obsidian/__main__.py
notion2obsidian/n2o.py
notion2obsidian-0.1.1.dist-info/LICENSE
notion2obsidian-0.1.1.dist-info/METADATA
notion2obsidian-0.1.1.dist-info/WHEEL
notion2obsidian-0.1.1.dist-info/entry_points.txt
notion2obsidian-0.1.1.dist-info/top_level.txt
notion2obsidian-0.1.1.dist-info/RECORD
