Metadata-Version: 2.1
Name: notion2obsidian
Version: 0.1.1
Summary: Convert Notion md files to Obsidian md files.
Home-page: https://github.com/butterandfly/notion2obsidian
Author: butterandfly
Author-email: zero.hero.lin@gmail.com
License: MIT
Classifier: License :: OSI Approved :: MIT License
Classifier: Programming Language :: Python :: 3
Classifier: Programming Language :: Python :: 3.9
License-File: LICENSE
Requires-Dist: rich
